{
    "properties": {
        "name": "ListFinanceOp",
        "environment": {
            "type": "noflo-nodejs"
        },
        "icon": "list"
    },
    "inports": {
        "req": {
            "process": "List",
            "port": "req",
            "metadata": {
                "x": 190,
                "y": 100,
                "width": 72,
                "height": 72
            }
        },
        "type": {
            "process": "FetchList",
            "port": "name",
            "metadata": {
                "x": 180,
                "y": 396,
                "width": 72,
                "height": 72
            }
        }
    },
    "outports": {},
    "groups": [],
    "processes": {
        "List": {
            "component": "aretecode_finance/List",
            "metadata": {
                "label": "List",
                "x": 334,
                "y": 100,
                "width": 72,
                "height": 72
            }
        },
        "FetchList": {
            "component": "aretecode_finance/FetchList",
            "metadata": {
                "label": "FetchList",
                "x": 576,
                "y": 396,
                "width": 72,
                "height": 72
            }
        },
        "Response": {
            "component": "aretecode_finance/Response",
            "metadata": {
                "label": "Response",
                "x": 864,
                "y": 288,
                "width": 72,
                "height": 72
            }
        },
        "FetchListError": {
            "component": "core/Output",
            "metadata": {
                "label": "FetchListError",
                "x": 720,
                "y": 504,
                "width": 72,
                "height": 72
            }
        },
        "ResponseListError": {
            "component": "core/Output",
            "metadata": {
                "label": "ResponseListError",
                "x": 1044,
                "y": 324,
                "width": 72,
                "height": 72
            }
        },
        "ListError": {
            "component": "core/Output",
            "metadata": {
                "label": "ListError",
                "x": 468,
                "y": -36,
                "width": 72,
                "height": 72
            }
        }
    },
    "connections": [
        {
            "src": {
                "process": "List",
                "port": "res"
            },
            "tgt": {
                "process": "Response",
                "port": "res"
            },
            "metadata": {
                "route": 9
            }
        },
        {
            "src": {
                "process": "List",
                "port": "out"
            },
            "tgt": {
                "process": "FetchList",
                "port": "in"
            },
            "metadata": {
                "route": 7
            }
        },
        {
            "src": {
                "process": "FetchList",
                "port": "out"
            },
            "tgt": {
                "process": "Response",
                "port": "retrieved"
            },
            "metadata": {
                "route": 6
            }
        },
        {
            "src": {
                "process": "FetchList",
                "port": "error"
            },
            "tgt": {
                "process": "FetchListError",
                "port": "in"
            },
            "metadata": {
                "route": 1
            }
        },
        {
            "src": {
                "process": "Response",
                "port": "error"
            },
            "tgt": {
                "process": "ResponseListError",
                "port": "in"
            },
            "metadata": {
                "route": 1
            }
        },
        {
            "src": {
                "process": "List",
                "port": "error"
            },
            "tgt": {
                "process": "ListError",
                "port": "in"
            },
            "metadata": {
                "route": 1
            }
        }
    ]
}
