{
    "properties": {
        "name": "MonthlyReport",
        "environment": {
            "type": "noflo-nodejs"
        },
        "icon": ""
    },
    "inports": {
        "req": {
            "process": "Monthly",
            "port": "req",
            "metadata": {
                "x": 144,
                "y": 108,
                "width": 72,
                "height": 72
            }
        },
        "type": {
            "process": "FetchW/MonthYear",
            "port": "name",
            "metadata": {
                "x": 144,
                "y": 252,
                "width": 72,
                "height": 72
            }
        }
    },
    "outports": {},
    "groups": [],
    "processes": {
        "FetchW/MonthYear": {
            "component": "finance/FetchWithMonthYear",
            "metadata": {
                "label": "FetchW/MonthYear",
                "x": 504,
                "y": 216,
                "width": 72,
                "height": 72
            }
        },
        "Monthly": {
            "component": "finance/Monthly",
            "metadata": {
                "label": "Monthly",
                "x": 288,
                "y": 36,
                "width": 72,
                "height": 72
            }
        },
        "Response": {
            "component": "finance/Response",
            "metadata": {
                "label": "Response",
                "x": 720,
                "y": 36,
                "width": 72,
                "height": 72
            }
        },
        "MonthYearError": {
            "component": "core/Output",
            "metadata": {
                "label": "MonthYearError",
                "x": 684,
                "y": 252,
                "width": 72,
                "height": 72
            }
        },
        "MonthlyError": {
            "component": "core/Output",
            "metadata": {
                "label": "MonthlyError",
                "x": 396,
                "y": -72,
                "width": 72,
                "height": 72
            }
        }
    },
    "connections": [
        {
            "src": {
                "process": "Monthly",
                "port": "out"
            },
            "tgt": {
                "process": "FetchW/MonthYear",
                "port": "in"
            },
            "metadata": {
                "route": 10
            }
        },
        {
            "src": {
                "process": "FetchW/MonthYear",
                "port": "out"
            },
            "tgt": {
                "process": "Response",
                "port": "monthly"
            },
            "metadata": {
                "route": 10
            }
        },
        {
            "src": {
                "process": "Monthly",
                "port": "res"
            },
            "tgt": {
                "process": "Response",
                "port": "res"
            },
            "metadata": {
                "route": 5
            }
        },
        {
            "src": {
                "process": "FetchW/MonthYear",
                "port": "error"
            },
            "tgt": {
                "process": "MonthYearError",
                "port": "in"
            },
            "metadata": {
                "route": 1
            }
        },
        {
            "src": {
                "process": "Monthly",
                "port": "error"
            },
            "tgt": {
                "process": "MonthlyError",
                "port": "in"
            },
            "metadata": {
                "route": 1
            }
        }
    ]
}
